proyecto_bu/__init__.py
proyecto_bu-0.0.1.dist-info/METADATA
proyecto_bu-0.0.1.dist-info/WHEEL
proyecto_bu-0.0.1.dist-info/top_level.txt
proyecto_bu-0.0.1.dist-info/RECORD
